spark_utils/__init__.py
spark_utils/_version.py
spark_utils/common/__init__.py
spark_utils/common/functions.py
spark_utils/common/spark_job_args.py
spark_utils/common/spark_session_provider.py
spark_utils/common/spark_sql_utils.py
spark_utils/common/spark_udf.py
spark_utils/dataframes/__init__.py
spark_utils/dataframes/functions.py
spark_utils/dataframes/models.py
spark_utils/dataframes/sets/__init__.py
spark_utils/dataframes/sets/functions.py
spark_utils/delta_lake/__init__.py
spark_utils/delta_lake/delta_log.py
spark_utils/delta_lake/functions.py
spark_utils/models/__init__.py
spark_utils/models/delta_lake_config.py
spark_utils/models/hive_metastore_config.py
spark_utils/models/hive_table.py
spark_utils/models/iceberg_rest_config.py
spark_utils/models/job_socket.py
spark_utils/models/k8s_config.py
spark_utils-2.0.2.dist-info/METADATA
spark_utils-2.0.2.dist-info/WHEEL
spark_utils-2.0.2.dist-info/licenses/LICENSE
spark_utils-2.0.2.dist-info/RECORD
