Metadata-Version: 2.4
Name: spark-utils
Version: 2.0.2
Summary: Utility classes for comfy Spark job authoriing.
License: MIT
License-File: LICENSE
Author: ECCO Sneaks & Data
Author-email: esdsupport@ecco.com
Maintainer: GZU
Maintainer-email: gzu@ecco.com
Requires-Python: >=3.11,<3.13
Classifier: License :: OSI Approved :: MIT License
Classifier: Programming Language :: Python :: 3
Classifier: Programming Language :: Python :: 3.11
Classifier: Programming Language :: Python :: 3.12
Provides-Extra: delta
Provides-Extra: k8s
Requires-Dist: backoff (>=2.2,<2.3)
Requires-Dist: cryptography (>=36)
Requires-Dist: delta-spark (>=3.2.1,<3.3.0) ; extra == "delta"
Requires-Dist: hadoop-fs-wrapper (>=0.7,<0.8)
Requires-Dist: kubernetes (>=34,<35) ; extra == "k8s"
Project-URL: Repository, https://github.com/SneaksAndData/spark-utils
